[{"s": "iis-ili-brokerskij-schet-chto-luchshe-vtb", "t": "ИИС или брокерский счёт в ВТБ: что выгоднее в 2026 году?", "i": "📈", "c": "investitsii"}, {"s": "iis-vtb-dlya-chego", "t": "ИИС ВТБ: для чего нужен, как открыть и получить налоговый вычет", "i": "📈", "c": "investitsii"}, {"s": "iis-vtb-s-kakogo-vozrasta", "t": "ИИС ВТБ: с какого возраста можно открыть в 2026 году?", "i": "📈", "c": "investitsii"}, {"s": "iis-v-vtb-ili-tinkoff-gde-luchshe", "t": "ИИС в ВТБ или Тинькофф: где лучше открыть в 2026 году?", "i": "📈", "c": "investitsii"}, {"s": "iis-chto-eto-takoe-v-vtb-i-kak-rabotaet-dlya-chajnikov", "t": "ИИС в ВТБ: что это и как работает простыми словами", "i": "📈", "c": "investitsii"}, {"s": "iis-kak-zakryt-v-vtb", "t": "Как закрыть ИИС в ВТБ: пошаговая инструкция 2026 года", "i": "📈", "c": "investitsii"}, {"s": "iis-vtb-chto-eto-i-kak-rabotaet-plyusy-minusy", "t": "ИИС ВТБ 2026: что это, как работает, плюсы и минусы для инвестора", "i": "📈", "c": "investitsii"}, {"s": "iis-srochnyj-i-osnovnoj-vtb-raznitsa-v-chem-zaklyuchaetsya", "t": "ИИС в ВТБ: чем срочный отличается от основного в 2026 году", "i": "📈", "c": "investitsii"}, {"s": "iis-chto-eto-i-kak-rabotaet-v-vtb-otzyvy", "t": "ИИС в ВТБ: что это, как работает, отзывы клиентов 2026", "i": "📈", "c": "investitsii"}, {"s": "iis-vtb-kuda-prikhodyat-dividendy", "t": "ИИС ВТБ: куда приходят дивиденды и как их получить в 2026 году", "i": "📈", "c": "investitsii"}, {"s": "iis-v-vtb-chto-eto-i-kak-rabotaet", "t": "ИИС в ВТБ: что это, как работает и как открыть в 2026 году", "i": "📈", "c": "investitsii"}, {"s": "iis-vtb-kak-otkryt-poshagovaya", "t": "Как открыть ИИС в ВТБ: пошаговая инструкция 2026 года", "i": "📈", "c": "investitsii"}, {"s": "iis-srochnyj-chto-eto-vtb", "t": "ИИС Срочный ВТБ 2026: что это, условия, проценты и как открыть", "i": "📈", "c": "investitsii"}, {"s": "iis-vtb-chto-eto-kak-poluchit", "t": "ИИС ВТБ: что это, как открыть и получить налоговый вычет в 2026 году", "i": "📈", "c": "investitsii"}, {"s": "iis-v-vtb-chto-delat-sejchas", "t": "ИИС в ВТБ 2026: что делать сейчас — инструкция для инвесторов", "i": "📈", "c": "investitsii"}, {"s": "iis-vtb-gde-posmotret", "t": "Где посмотреть ИИС в ВТБ: личный кабинет, приложение и офисы", "i": "📈", "c": "investitsii"}, {"s": "iis-vtb-eto-chto", "t": "ИИС ВТБ — что это такое и как открыть в 2026 году", "i": "📈", "c": "investitsii"}, {"s": "iis-vtb-chto-eto-takoe-i-kak-eto-rabotaet", "t": "ИИС ВТБ: что это, как работает и как открыть в 2026 году", "i": "📈", "c": "investitsii"}, {"s": "iis-ili-brokerskij-schet-chto-luchshe-dlya-nachinayushchikh-vtb-24", "t": "ИИС или брокерский счет в ВТБ 24: что выбрать начинающему инвестору?", "i": "📈", "c": "investitsii"}, {"s": "iin-v-vtb-chto-eto-takoe", "t": "ИИН в ВТБ: что это такое и как его найти в 2026 году", "i": "💳", "c": "karty-i-scheta"}, {"s": "iis-v-vtb-investitsii-kak-otkryt", "t": "ИИС в ВТБ Инвестиции: как открыть онлайн за 15 минут (2026)", "i": "📈", "c": "investitsii"}, {"s": "iis-vtb-chto-eto-takoe-i-kak-eto-rabotaet-otzyvy-pokupatelej", "t": "ИИС ВТБ 2026: что это, как работает, отзывы клиентов и реальные условия", "i": "📈", "c": "investitsii"}, {"s": "iis-vtb-zachem", "t": "ИИС ВТБ: зачем нужен, условия и доходность 2026", "i": "📈", "c": "investitsii"}, {"s": "iis-chto-eto-vtb-otkrytie", "t": "ИИС в ВТБ и Открытии: условия, лимиты и типы вычетов", "i": "📈", "c": "investitsii"}, {"s": "iis-chto-eto-i-kak-rabotaet-v-vtb-plyusy-i-minusy-otzyvy", "t": "ИИС в ВТБ: что это, условия, плюсы и минусы в 2026", "i": "📈", "c": "investitsii"}, {"s": "iis-vtb-gde-otobrazhaetsya", "t": "Где найти ИИС ВТБ: отображение в приложении и на сайте", "i": "📈", "c": "investitsii"}, {"s": "iis-v-vtb-kak-otkryt-poshagovaya-instruktsiya", "t": "ИИС в ВТБ: как открыть счет и получить бонусы", "i": "📈", "c": "investitsii"}, {"s": "iis-v-rublyakh-vtb-chto-eto", "t": "ИИС в рублях ВТБ: что это, доходность и условия 2026", "i": "📈", "c": "investitsii"}, {"s": "iis-vtb-chto-eto-takoe-i-kak-eto-rabotaet-otzyvy", "t": "ИИС ВТБ: что это, условия открытия и отзывы клиентов", "i": "📈", "c": "investitsii"}, {"s": "iis-chto-eto-i-kak-rabotaet-v-vtb-otzyvy-sotrudnikov", "t": "ИИС в ВТБ: отзывы сотрудников о работе и условия 2026", "i": "📁", "c": null}]