[{"s": "kak-bez-komissii-perevesti-dengi-so-sberbanka-na-vtb-cherez-mobilnoe", "t": "Как перевести деньги без комиссии со Сбербанка на ВТБ через телефон", "i": "💸", "c": "perevody"}, {"s": "kak-bystro-kupit-kvartiru-s-ipotekoj-vtb", "t": "Как быстро купить квартиру с ипотекой ВТБ в 2026 году: пошаговая инструкция", "i": "🏠", "c": "ipoteka"}, {"s": "kak-bystro-odobryayut-ipoteku-v-vtb-24", "t": "Сроки одобрения ипотеки в ВТБ: как ускорить процесс в 2026 году", "i": "🏠", "c": "ipoteka"}, {"s": "kak-bystro-poluchit-kredit-v-vtb", "t": "Как быстро получить кредит в ВТБ: пошаговая инструкция 2026", "i": "📉", "c": "kredity"}, {"s": "kak-banki-rassmatrivayut-zayavki-na-kredit-v-vtb-24", "t": "Как ВТБ 24 рассматривает заявки на кредит: алгоритм и секреты одобрения", "i": "📉", "c": "kredity"}, {"s": "kak-beskontaktno-oplatit-s-telefona-vtb", "t": "Как оплатить бесконтактно с телефона ВТБ: пошаговая инструкция 2026", "i": "💳", "c": "karty-i-scheta"}, {"s": "kak-broker-vtb-uderzhivaet-ndfl", "t": "Как ВТБ удерживает НДФЛ: порядок, сроки и нюансы для клиентов 2026", "i": "📈", "c": "investitsii"}, {"s": "kak-bystree-vyplatit-kredit-v-vtb", "t": "Как быстрее погасить кредит в ВТБ: 7 работающих способов 2026", "i": "📉", "c": "kredity"}, {"s": "kak-bystro-pogasit-ipoteku-v-vtb-pri-annuitetnykh-platezhakh", "t": "Как быстро погасить ипотеку ВТБ с аннуитетными платежами: 7 способов", "i": "🏠", "c": "ipoteka"}, {"s": "kak-bystro-svyazatsya-s-operatorom-vtb", "t": "Как быстро связаться с оператором ВТБ: 7 способов 2026", "i": "📍", "c": "ofisy-i-bankomaty"}, {"s": "kak-bystro-uznat-balans-karty-vtb", "t": "Как проверить баланс карты ВТБ за 1 минуту: 7 быстрых способов", "i": "💳", "c": "karty-i-scheta"}, {"s": "kak-bystro-vyplatit-ipoteku-v-vtb-sovety", "t": "Как быстро погасить ипотеку в ВТБ: 10 проверенных способов 2026", "i": "🏠", "c": "ipoteka"}, {"s": "kak-beskontaktno-snyat-dengi-s-karty-v-bankomate-vtb", "t": "Как снять деньги с карты ВТБ без карты: инструкция 2026", "i": "📍", "c": "ofisy-i-bankomaty"}, {"s": "kak-bez-protsentov-perevesti-dengi-s-karty-vtb-na-kartu-drugogo-banka", "t": "Как перевести деньги с карты ВТБ без комиссии — 5 способов 2026", "i": "💸", "c": "perevody"}, {"s": "kak-bystree-vyplatit-ipoteku-v-vtb", "t": "Как быстрее выплатить ипотеку в ВТБ: 7 проверенных способов", "i": "🏠", "c": "ipoteka"}, {"s": "kak-bystro-zakryt-kredit-v-vtb", "t": "Как быстро закрыть кредит в ВТБ: пошаговая инструкция 2026", "i": "📉", "c": "kredity"}, {"s": "kak-blokirovat-kartu-vtb-cherez-prilozhenie", "t": "Как заблокировать карту ВТБ через приложение за 3 минуты", "i": "🔒", "c": "bezopasnost"}, {"s": "kak-bonusy-vtb-prevratit-v-dengi-na-kartu-vtb-perevesti", "t": "Как обналичить бонусы ВТБ на карту: пошаговая инструкция 2026", "i": "🎁", "c": "bonusy"}, {"s": "kak-bystro-oformlyaetsya-ipoteka-v-vtb", "t": "Как быстро оформить ипотеку в ВТБ в 2026: сроки и пошаговая инструкция", "i": "🏠", "c": "ipoteka"}, {"s": "kak-bez-komissii-perevesti-dengi-s-vtb-na-sberbank-cherez-bystrye-platezhi", "t": "Как перевести деньги с ВТБ на Сбербанк без комиссии через СПБ", "i": "💸", "c": "perevody"}, {"s": "kak-bonusami-vtb-oplatit-mobilnuyu-svyaz-tele2", "t": "Как оплатить Теле2 бонусами ВТБ: пошаговая инструкция 2026", "i": "🎁", "c": "bonusy"}, {"s": "kak-besplatno-pokatatsya-na-velosipede-vtb", "t": "Как бесплатно покататься на велосипеде ВТБ в 2026 году: 5 проверенных способов", "i": "🎁", "c": "bonusy"}, {"s": "kak-besprotsentno-perevesti-dengi-s-vtb-na-sberbank", "t": "Как перевести деньги с ВТБ на Сбербанк без комиссии — 5 способов 2026", "i": "💸", "c": "perevody"}, {"s": "kak-bez-komissii-perevesti-dengi-so-sberbanka-na-vtb-svoej-karty", "t": "Как перевести деньги со Сбербанка на ВТБ без комиссии в 2026 году", "i": "💸", "c": "perevody"}, {"s": "kak-bez-komissii-vyvesti-dengi-s-kreditnoj-karty-vtb", "t": "Как вывести деньги с кредитки ВТБ без комиссии — 5 проверенных способов 2026", "i": "💳", "c": "karty-i-scheta"}, {"s": "kak-brat-velosiped-vtb", "t": "Как взять велосипед в аренду от ВТБ: условия и пошаговая инструкция 2026", "i": "📁", "c": "drugoe"}, {"s": "kak-bystro-pogasit-kreditnuyu-kartu-vtb-24", "t": "Как быстро погасить кредитную карту ВТБ 24: 7 проверенных способов", "i": "📉", "c": "kredity"}, {"s": "kak-bystro-zakryt-kreditnuyu-kartu-vtb-24", "t": "Как быстро закрыть кредитную карту ВТБ 24: пошаговая инструкция 2026", "i": "💳", "c": "karty-i-scheta"}, {"s": "kak-beskontaktno-oplatit-s-telefona-vtb-kartoj", "t": "Как оплатить бесконтактно с телефона картой ВТБ: пошаговая инструкция 2026", "i": "💳", "c": "karty-i-scheta"}, {"s": "kak-bez-protsentov-perevesti-dengi-s-vtb-na-kartu-sberbanka", "t": "Как перевести деньги с ВТБ на Сбербанк без комиссии — 5 способов 2026", "i": "💸", "c": "perevody"}, {"s": "kak-bystrej-vyplatit-ipoteku-vtb", "t": "Как быстрее погасить ипотеку в ВТБ: 10 проверенных способов 2026", "i": "🏠", "c": "ipoteka"}, {"s": "kak-bystro-mozhno-poluchit-kartu-vtb-bank", "t": "Как быстро получить карту ВТБ: сроки и способы оформления 2026", "i": "💳", "c": "karty-i-scheta"}, {"s": "kak-bystro-nachislyayutsya-bonusy-v-vtb", "t": "Как быстро начисляются бонусы ВТБ: сроки и условия в 2026 году", "i": "🎁", "c": "bonusy"}, {"s": "kak-bystro-prikhodyat-dengi-s-karty-vtb-na-kartu-sberbanka", "t": "Скорость перевода с карты ВТБ на Сбербанк в 2026: сроки и нюансы", "i": "💸", "c": "perevody"}, {"s": "kak-blokirovat-kreditnuyu-kartu-vtb", "t": "Как заблокировать карту ВТБ быстро: 5 способов в 2026 году", "i": "🔒", "c": "bezopasnost"}, {"s": "kak-bonusami-vtb-oplatit-mobilnuyu-svyaz-mts", "t": "Как оплатить МТС бонусами ВТБ: пошаговая инструкция 2026", "i": "🎁", "c": "bonusy"}, {"s": "kak-bystro-delayut-debetovuyu-kartu-v-vtb", "t": "Как быстро делают дебетовую карту в ВТБ: сроки и способы получения", "i": "💳", "c": "karty-i-scheta"}, {"s": "kak-bystro-snyat-obremenenie-s-kvartiry-posle-pogasheniya-ipoteki-vtb", "t": "Как снять обременение с квартиры после погашения ипотеки ВТБ в 2026 году", "i": "🏠", "c": "ipoteka"}, {"s": "kak-bank-vtb-rabotaet", "t": "Как работает ВТБ в 2026: услуги, тарифы и возможности для клиентов", "i": "📁", "c": "drugoe"}, {"s": "kak-bystro-pogasit-kredit-v-vtb-sovety", "t": "Как быстро погасить кредит в ВТБ: 7 проверенных способов 2026", "i": "📉", "c": "kredity"}, {"s": "kak-bystro-vtb-daet-otvet-po-ipoteke", "t": "Сколько ждать ответ по ипотеке в ВТБ в 2026 году? Сроки и нюансы", "i": "🏠", "c": "ipoteka"}, {"s": "kak-bonusy-vtb-prevratit-v-dengi", "t": "Как обналичить бонусы ВТБ: 5 проверенных способов 2026", "i": "🎁", "c": "bonusy"}, {"s": "kak-bystro-snimayut-dengi-s-arestovannoj-karty-vtb-24", "t": "Как быстро снять деньги с арестованной карты ВТБ 24: пошаговая инструкция 2026", "i": "💳", "c": "karty-i-scheta"}, {"s": "kak-bystro-vyplatit-ipoteku-v-vtb-24-sovety", "t": "Как быстро погасить ипотеку в ВТБ: 24 проверенных совета 2026", "i": "🏠", "c": "ipoteka"}, {"s": "kak-bystree-zakryt-ipoteku-v-vtb", "t": "Как быстрее закрыть ипотеку в ВТБ: 7 проверенных способов 2026", "i": "🏠", "c": "ipoteka"}, {"s": "kak-bystro-spisyvayutsya-dengi-s-arestovannoj-karty-vtb", "t": "Как быстро списываются деньги с арестованной карты ВТБ в 2026 году", "i": "💳", "c": "karty-i-scheta"}, {"s": "kak-bystro-vtb-podaet-v-sud-na-dolzhnika", "t": "Через сколько ВТБ подает в суд на должника в 2026 году? Сроки и алгоритм", "i": "📉", "c": "kredity"}, {"s": "kak-bystro-zabrat-zakladnuyu-v-vtb", "t": "Как быстро забрать закладную из ВТБ: пошаговая инструкция 2026", "i": "🏠", "c": "ipoteka"}, {"s": "kak-beretsya-avtokredit-v-vtb", "t": "Как взять автокредит в ВТБ в 2026 году: пошаговая инструкция", "i": "📉", "c": "kredity"}, {"s": "kak-bez-komissii-perevesti-s-vtb-na-sberbank-cherez-onlajn-bank", "t": "Как перевести с ВТБ на Сбербанк без комиссии через онлайн-банк 2026", "i": "💸", "c": "perevody"}, {"s": "kak-bez-protsentov-perevesti-dengi-so-sberbanka-na-vtb-bez-komissii-s-karty", "t": "Как перевести деньги со Сбербанка на ВТБ без комиссии — 5 способов 2026", "i": "💸", "c": "perevody"}, {"s": "kak-brat-kredit-vtb", "t": "Как взять кредит в ВТБ в 2026 году: пошаговая инструкция", "i": "📉", "c": "kredity"}, {"s": "kak-bystree-pogasit-kreditku-vtb", "t": "Как погасить кредитку ВТБ быстрее: 7 работающих способов 2026", "i": "📉", "c": "kredity"}, {"s": "kak-bystro-idet-perevod-s-vtb-na-sberbank", "t": "Скорость перевода с ВТБ на Сбербанк: сроки и нюансы 2026", "i": "💸", "c": "perevody"}, {"s": "kak-bystro-otkryvaetsya-akkreditiv-v-vtb", "t": "Сроки открытия аккредитива в ВТБ: от 1 дня до 5 рабочих", "i": "💸", "c": "perevody"}, {"s": "kak-bystro-prikhodyat-dengi-so-sberbanka-na-vtb", "t": "Скорость перевода со Сбербанка на ВТБ: сроки и нюансы 2026", "i": "💸", "c": "perevody"}, {"s": "kak-besplatno-perevodit-dengi-s-vtb-na-sberbank-bez-komissii", "t": "Как перевести деньги с ВТБ на Сбербанк без комиссии в 2026 году", "i": "💸", "c": "perevody"}, {"s": "kak-bystro-delayut-kartu-vtb", "t": "Сроки изготовления карты ВТБ в 2026: как ускорить процесс", "i": "💳", "c": "karty-i-scheta"}, {"s": "kak-bystro-pogasit-kredit-v-banke-vtb", "t": "Как быстро погасить кредит в ВТБ: 7 проверенных способов 2026", "i": "📉", "c": "kredity"}, {"s": "kak-bystro-zakryt-ipoteku-v-banke-vtb", "t": "Как быстро закрыть ипотеку в ВТБ: 7 проверенных способов 2026", "i": "🏠", "c": "ipoteka"}, {"s": "kak-bez-komissii-snyat-dengi-s-kreditnoj-karty-vtb", "t": "Как снять деньги с кредитки ВТБ без комиссии: 7 проверенных способов", "i": "💳", "c": "karty-i-scheta"}, {"s": "kak-bystro-proverit-balans-vtb", "t": "Как проверить баланс ВТБ за 1 минуту: 7 способов онлайн и офлайн", "i": "💳", "c": "karty-i-scheta"}, {"s": "kak-bystro-vtb-snimaet-arest-s-karty", "t": "Как быстро ВТБ снимает арест с карты: сроки и инструкции 2026", "i": "💳", "c": "karty-i-scheta"}, {"s": "kak-bystree-pogasit-ipoteku-v-vtb-i-vygodnee", "t": "Как быстрее погасить ипотеку в ВТБ: 7 проверенных способов", "i": "🏠", "c": "ipoteka"}, {"s": "kak-bystro-poluchit-kredit-v-vtb-24", "t": "Как быстро взять кредит в ВТБ 24: пошаговая инструкция 2026", "i": "📉", "c": "kredity"}, {"s": "kak-bystro-vtb-odobryaet-ipoteku-zarplatnym-klientam", "t": "Сроки одобрения ипотеки ВТБ для зарплатных клиентов в 2026 году", "i": "🏠", "c": "ipoteka"}, {"s": "kak-bystro-vtb-snimaet-arest", "t": "Сроки снятия ареста с карты ВТБ в 2026 году: пошаговая инструкция", "i": "💳", "c": "karty-i-scheta"}, {"s": "kak-besplatno-perevesti-dengi-s-karty-sberbanka-na-kartu-vtb-bez-komissii-onlajn", "t": "Как перевести деньги с Сбербанка на ВТБ без комиссии в 2026 году", "i": "💸", "c": "perevody"}, {"s": "kak-bez-protsentov-perevesti-dengi-so-sberbanka-na-vtb-bez-komissii-s-karty-na-kartu", "t": "Как перевести деньги с Сбербанка на ВТБ без комиссии в 2026 году", "i": "💸", "c": "perevody"}, {"s": "kak-bystro-delayut-zarplatnuyu-kartu-vtb", "t": "Сколько делают зарплатную карту ВТБ в 2026 году: сроки и способы", "i": "💳", "c": "karty-i-scheta"}, {"s": "kak-bystro-dozvonitsya-operatoru-vtb", "t": "Как быстро дозвониться оператору ВТБ: горячие номера и лайфхаки", "i": "📁", "c": "drugoe"}, {"s": "kak-bystro-vtb-snimaet-obremenenie-s-kvartiry", "t": "Сроки снятия обременения ВТБ с квартиры в 2026 году: пошаговый разбор", "i": "🏠", "c": "ipoteka"}, {"s": "kak-bez-karty-polozhit-dengi-v-bankomate-vtb", "t": "Как положить деньги в банкомат ВТБ без карты: 5 способов 2026", "i": "📍", "c": "ofisy-i-bankomaty"}, {"s": "kak-bezopasno-obnovit-vtb-prilozhenie", "t": "Как безопасно обновить приложение ВТБ: пошаговая инструкция 2026", "i": "📱", "c": "mobilnyj-bank"}, {"s": "kak-bystro-oformit-kreditnuyu-kartu-vtb", "t": "Как быстро оформить кредитную карту ВТБ: пошаговая инструкция 2026", "i": "💳", "c": "karty-i-scheta"}, {"s": "kak-bystro-oformlyayut-ipoteku-v-vtb", "t": "Как быстро оформить ипотеку в ВТБ: сроки и пошаговая инструкция 2026", "i": "🏠", "c": "ipoteka"}, {"s": "kak-bez-protsentov-perevesti-dengi-s-karty-vtb-na-kartu-sberbanka-bez-komissii", "t": "Как перевести деньги с ВТБ на Сбербанк без комиссии и процентов", "i": "💸", "c": "perevody"}, {"s": "kak-bystree-zakryt-kredit-v-vtb", "t": "Как быстрее закрыть кредит в ВТБ: 7 работающих способов 2026", "i": "📉", "c": "kredity"}, {"s": "kak-bystro-dayut-ipoteku-v-vtb", "t": "Сколько времени дают ипотеку в ВТБ в 2026 году: сроки и этапы", "i": "🏠", "c": "ipoteka"}, {"s": "kak-bystro-oformit-kartu-vtb", "t": "Как быстро оформить карту ВТБ: пошаговая инструкция 2026", "i": "💳", "c": "karty-i-scheta"}, {"s": "kak-bystro-oplatit-kredit-vtb", "t": "Как быстро погасить кредит ВТБ: 7 способов без комиссий", "i": "📉", "c": "kredity"}, {"s": "kak-bystro-pensionnyj-fond-perechislyaet-dengi-po-materinskomu-kapitalu-na-ipoteku-v-vtb", "t": "Сроки перечисления маткапитала на ипотеку ВТБ в 2026 году: пошаговый разбор", "i": "🏠", "c": "ipoteka"}, {"s": "kak-bonusy-vtb-perevesti-v-rubli-na-kartu-cherez-prilozhenie-vtb-onlajn", "t": "Как перевести бонусы ВТБ в рубли на карту через приложение ВТБ Онлайн", "i": "🎁", "c": "bonusy"}, {"s": "kak-bystro-snimaetsya-obremenenie-s-kvartiry-posle-pogasheniya-ipoteki-vtb", "t": "Снятие обременения с квартиры после погашения ипотеки ВТБ: сроки и порядок", "i": "🏠", "c": "ipoteka"}, {"s": "kak-bystro-snimayut-arest-s-karty-vtb", "t": "Как быстро снять арест с карты ВТБ: пошаговая инструкция 2026", "i": "💳", "c": "karty-i-scheta"}, {"s": "kak-bystro-snyat-dengi-s-arestovannoj-karty-vtb", "t": "Как снять деньги с арестованной карты ВТБ — законные способы 2026", "i": "💳", "c": "karty-i-scheta"}, {"s": "kak-bystro-vyplatit-kreditnuyu-kartu-vtb", "t": "Как быстро погасить кредитную карту ВТБ: 7 работающих способов", "i": "📉", "c": "kredity"}, {"s": "kak-bystro-zachislyayutsya-dengi-na-kartu-vtb", "t": "Скорость зачисления денег на карту ВТБ: сроки и нюансы", "i": "💸", "c": "perevody"}, {"s": "kak-bank-vtb-ukral-u-menya-dengi", "t": "ВТБ украл деньги: как вернуть средства и защититься от мошенников в 2026", "i": "🔒", "c": "bezopasnost"}, {"s": "kak-besplatno-perevesti-s-vtb-na-sberbank-bez-komissii", "t": "Как перевести с ВТБ на Сбербанк без комиссии — 5 способов 2026", "i": "💸", "c": "perevody"}, {"s": "kak-bez-komissii-perevesti-dengi-s-vtb-na-sberbank-cherez-onlajn-bank-po-nomeru-karty", "t": "Как перевести деньги с ВТБ на Сбербанк без комиссии — пошаговая инструкция 2026", "i": "💸", "c": "perevody"}, {"s": "kak-bez-protsentov-perevesti-dengi-so-sberbanka-na-vtb-bez-komissii-cherez-telefon", "t": "Как перевести деньги со Сбербанка на ВТБ без комиссии через телефон в 2026 году", "i": "💸", "c": "perevody"}, {"s": "kak-bonusy-spasibo-perevesti-v-dengi-na-kartu-vtb-24", "t": "Как перевести бонусы Спасибо от ВТБ в деньги на карту в 2026 году", "i": "🎁", "c": "bonusy"}, {"s": "kak-brat-velosipedy-vtb-naprokat-v-moskve", "t": "Как взять велосипед ВТБ напрокат в Москве: пошаговая инструкция 2026", "i": "📁", "c": "drugoe"}, {"s": "kak-bystree-rasschitatsya-s-ipotekoj-vtb-bank", "t": "Как быстрее погасить ипотеку в ВТБ: 7 работающих способов 2026", "i": "🏠", "c": "ipoteka"}, {"s": "kak-bez-komissii-perevesti-dengi-na-kartu-vtb", "t": "Как перевести деньги на карту ВТБ без комиссии — 5 способов 2026", "i": "💸", "c": "perevody"}, {"s": "kak-brat-v-arendu-velosipedy-vtb", "t": "Аренда велосипедов ВТБ: условия, цены и как оформить за 5 минут", "i": "💳", "c": "karty-i-scheta"}, {"s": "kak-brat-v-prokat-velosiped-vtb", "t": "Как взять велосипед в прокат от ВТБ: пошаговая инструкция 2026", "i": "📁", "c": "drugoe"}, {"s": "kak-brat-velik-vtb", "t": "Как взять велосипед в кредит в ВТБ: пошаговая инструкция 2026", "i": "📉", "c": "kredity"}, {"s": "kak-bystro-oplatit-kredit-vtb-24", "t": "Как быстро погасить кредит ВТБ 24: 7 способов без комиссий", "i": "📉", "c": "kredity"}, {"s": "kak-bystro-prikhodyat-dengi-na-schet-vtb", "t": "Скорость зачисления денег на счёт ВТБ: сроки и нюансы в 2026 году", "i": "💳", "c": "karty-i-scheta"}, {"s": "kak-bystro-spisyvayut-dengi-s-arestovannoj-karty-vtb", "t": "Как быстро списывают деньги с арестованной карты ВТБ в 2026 году", "i": "💳", "c": "karty-i-scheta"}, {"s": "kak-bystro-zablokirovat-kartu-vtb", "t": "Как быстро заблокировать карту ВТБ: 5 способов за 2 минуты", "i": "🔒", "c": "bezopasnost"}, {"s": "kak-bank-vtb-vybivaet-dolgi", "t": "Как ВТБ взыскивает долги: законные методы и ваши права", "i": "📉", "c": "kredity"}, {"s": "kak-besplatno-popolnit-kartu-vtb-multikarta-s-sberbanka", "t": "Как бесплатно пополнить ВТБ Мультикарту с карты Сбербанка в 2026 году", "i": "💸", "c": "perevody"}, {"s": "kak-bez-karty-snyat-dengi-v-bankomate-vtb-s-pomoshchyu-telefona", "t": "Как снять деньги в ВТБ без карты через телефон: пошаговая инструкция 2026", "i": "📍", "c": "ofisy-i-bankomaty"}, {"s": "kak-bez-komissii-perevesti-s-vtb-na-sberbank-cherez-mobilnyj", "t": "Как перевести с ВТБ на Сбербанк без комиссии через телефон: пошагово", "i": "💸", "c": "perevody"}, {"s": "kak-bez-protsentov-perevesti-dengi-s-vtb", "t": "Как перевести деньги с ВТБ без процентов: 7 проверенных способов", "i": "💸", "c": "perevody"}, {"s": "kak-bystree-vyplatit-ipoteku-v-vtb-sovety", "t": "Как быстрее погасить ипотеку в ВТБ: 10 работающих способов 2026", "i": "🏠", "c": "ipoteka"}, {"s": "kak-bystree-zakryt-kredit-v-vtb-24", "t": "Как быстро закрыть кредит в ВТБ: 7 проверенных способов 2026", "i": "📉", "c": "kredity"}, {"s": "kak-bystro-delayut-kartu-vtb-debetovaya", "t": "Сколько времени делается дебетовая карта ВТБ: сроки и способы получения", "i": "💳", "c": "karty-i-scheta"}, {"s": "kak-bystro-poluchit-kartu-mir-v-vtb", "t": "Как быстро оформить карту «Мир» в ВТБ: пошаговая инструкция 2026", "i": "💳", "c": "karty-i-scheta"}, {"s": "kak-bystro-prokhodit-elektronnaya-registratsiya-sdelki-v-rosreestre-cherez-vtb", "t": "Скорость электронной регистрации сделки в Росреестре через ВТБ в 2026", "i": "🏠", "c": "ipoteka"}, {"s": "kak-bystro-vtb-odobryaet-ipoteku-otzyvy", "t": "ВТБ ипотека: сроки одобрения 2026 + реальные отзывы клиентов", "i": "🏠", "c": "ipoteka"}, {"s": "kak-besplatno-perevesti-dengi-s-karty-vtb-na-kartu-sberbanka", "t": "Как перевести деньги с карты ВТБ на Сбербанк бесплатно — 5 способов 2026", "i": "💸", "c": "perevody"}, {"s": "kak-besplatno-perevesti-dengi-so-sberbanka-na-vtb-bez-komissii", "t": "Как перевести деньги со Сбербанка на ВТБ без комиссии бесплатно", "i": "💸", "c": "perevody"}, {"s": "kak-bez-komissii-perevesti-dengi-na-kartu-vtb-so-sberbanka", "t": "Как перевести деньги с Сбербанка на ВТБ без комиссии в 2026 году", "i": "💸", "c": "perevody"}, {"s": "kak-bez-komissii-perevesti-dengi-so-sberbanka-v-vtb-onlajn", "t": "Как перевести деньги со Сбербанка в ВТБ без комиссии — 2026", "i": "💸", "c": "perevody"}, {"s": "kak-bonusami-vtb-oplatit-mobilnuyu-svyaz", "t": "Как оплатить мобильную связь бонусами ВТБ: пошаговая инструкция 2026", "i": "🎁", "c": "bonusy"}, {"s": "kak-bystree-rasplatitsya-s-kreditom-v-vtb", "t": "Как быстрее погасить кредит в ВТБ: 7 работающих способов 2026", "i": "📉", "c": "kredity"}, {"s": "kak-bystro-pogasit-kreditnuyu-kartu-vtb", "t": "Как быстро погасить кредитную карту ВТБ: 7 рабочих способов", "i": "📉", "c": "kredity"}, {"s": "kak-bystro-vtb-perevodit-dengi-za-ipoteku-prodavtsu", "t": "Сроки перевода ВТБ по ипотеке продавцу в 2026 году: как ускорить", "i": "🏠", "c": "ipoteka"}, {"s": "kak-bystro-vyplatit-ipoteku-v-vtb-24", "t": "Как быстро погасить ипотеку в ВТБ: 7 работающих способов 2026", "i": "🏠", "c": "ipoteka"}, {"s": "kak-bally-multi-vtb-v-dengi-perevesti", "t": "Как перевести баллы Мульти ВТБ в деньги: пошаговая инструкция 2026", "i": "🎁", "c": "bonusy"}, {"s": "kak-beskontaktno-oplachivat-kartoj-vtb", "t": "Как оплачивать картой ВТБ без контакта: пошаговая инструкция 2026", "i": "💳", "c": "karty-i-scheta"}, {"s": "kak-blokirovat-kartu-vtb", "t": "Как заблокировать карту ВТБ: пошаговая инструкция 2026 года", "i": "🔒", "c": "bezopasnost"}, {"s": "kak-bonusnye-rubli-perevesti-v-dengi-vtb-24", "t": "Как обналичить бонусные рубли ВТБ 24 — 5 способов вывода в 2026 году", "i": "🎁", "c": "bonusy"}, {"s": "kak-bonusy-vtb-perevesti-na-kartu-po-shagovo", "t": "Как перевести бонусы ВТБ на карту — пошаговая инструкция 2026", "i": "🎁", "c": "bonusy"}, {"s": "kak-bystro-rassmatrivayut-zayavku-na-kredit-v-vtb", "t": "Скорость рассмотрения кредита в ВТБ: сроки и как ускорить процесс", "i": "📉", "c": "kredity"}, {"s": "kak-bystro-snimayut-arest-s-karty-sudebnye-pristavy-vtb", "t": "Как быстро снять арест с карты ВТБ: сроки и инструкция 2026", "i": "💳", "c": "karty-i-scheta"}, {"s": "kak-bystro-vtb-perevodit-dengi-po-ispolnitelnomu-listu", "t": "Сроки перевода ВТБ по исполнительному листу в 2026 году", "i": "💸", "c": "perevody"}, {"s": "kak-byt-krymchanam-s-kreditom-v-vtb-banke", "t": "Кредит ВТБ в Крыму 2026: что делать крымчанам с долгами", "i": "📉", "c": "kredity"}, {"s": "kak-bally-vtb-perevesti-v-dengi-na-kartu-multibonus", "t": "Как перевести баллы ВТБ в деньги на карту Мультибонус — пошаговая инструкция 2026", "i": "🎁", "c": "bonusy"}, {"s": "kak-bank-vtb-vzyskivaet-dolgi", "t": "Как ВТБ взыскивает долги по кредитам в 2026 году: этапы и советы", "i": "📉", "c": "kredity"}, {"s": "kak-bonusami-vtb-oplatit-mobilnuyu-svyaz-bilajn", "t": "Как оплатить Билайн бонусами ВТБ: пошаговая инструкция 2026", "i": "🎁", "c": "bonusy"}, {"s": "kak-bystro-oplatit-ipoteku-v-vtb-24", "t": "Как быстро погасить ипотеку в ВТБ: 7 проверенных способов 2026", "i": "🏠", "c": "ipoteka"}, {"s": "kak-bystro-pristavy-snimayut-dengi-s-karty-vtb", "t": "Как быстро приставы снимают деньги с карты ВТБ в 2026 году", "i": "💳", "c": "karty-i-scheta"}, {"s": "kak-bystro-prodat-kvartiru-v-ipoteke-vtb", "t": "Как быстро продать квартиру в ипотеке ВТБ: пошаговая инструкция 2026", "i": "🏠", "c": "ipoteka"}, {"s": "kak-bonusy-perevesti-v-rubli-v-vtb", "t": "Как обменять бонусы ВТБ на рубли в 2026: пошаговая инструкция", "i": "🎁", "c": "bonusy"}, {"s": "kak-bonusy-vtb-perevesti-v-rubli-2022", "t": "Как обналичить бонусы ВТБ в 2022: 5 проверенных способов", "i": "🎁", "c": "bonusy"}, {"s": "kak-bystro-snimayut-dengi-s-arestovannoj-karty-vtb", "t": "Как быстро снять деньги с арестованной карты ВТБ: законные способы 2026", "i": "💳", "c": "karty-i-scheta"}, {"s": "kak-bystro-zakryt-kredit-v-vtb-banke", "t": "Как быстро закрыть кредит в ВТБ: пошаговая инструкция 2026", "i": "📉", "c": "kredity"}, {"s": "kak-bonusy-vtb-prevratit-v-dengi-na-kartu", "t": "Как обналичить бонусы ВТБ на карту — 5 проверенных способов 2026", "i": "🎁", "c": "bonusy"}, {"s": "kak-bystro-bank-perechislyaet-dengi-po-ipoteke-prodavtsu-vtb", "t": "Сроки перечисления ипотеки продавцу в ВТБ: как ускорить процесс", "i": "🏠", "c": "ipoteka"}, {"s": "kak-bystro-rassmatrivayut-zayavku-na-ipoteku-v-vtb", "t": "Срок рассмотрения ипотеки в ВТБ в 2026 году: от 1 дня до 5 суток", "i": "🏠", "c": "ipoteka"}, {"s": "kak-bank-vtb-vzyskivaet-dolgi-po-kreditam", "t": "Как ВТБ взыскивает долги по кредитам в 2026: этапы, сроки и способы защиты", "i": "📉", "c": "kredity"}, {"s": "kak-besplatno-perevesti-dengi-so-sberbanka-na-vtb-bez-komissii-mezhdu-svoimi-schetami", "t": "Как перевести деньги со Сбербанка на ВТБ без комиссии — 2026", "i": "💸", "c": "perevody"}, {"s": "kak-bez-protsentov-perevesti-dengi-s-karty-sberbanka-na-vtb", "t": "Как перевести деньги с карты Сбербанка на ВТБ без процентов: 5 способов 2026", "i": "💸", "c": "perevody"}, {"s": "kak-bonusy-vtb-perevesti-v-rubli-na-kartu-2022", "t": "Как перевести бонусы ВТБ в рубли на карту в 2022 году — пошаговая инструкция", "i": "🎁", "c": "bonusy"}, {"s": "kak-brat-naprokat-velosiped-vtb", "t": "Как взять велосипед напрокат от ВТБ: пошаговая инструкция 2026", "i": "📁", "c": "drugoe"}, {"s": "kak-bystro-otkryvaetsya-brokerskij-schet-v-vtb", "t": "Как быстро открыть брокерский счёт в ВТБ: пошаговая инструкция 2026", "i": "📈", "c": "investitsii"}, {"s": "kak-besplatno-ezdit-na-avtobuse-po-karte-vtb", "t": "Как бесплатно ездить на автобусе по карте ВТБ: пошаговая инструкция 2026", "i": "🎁", "c": "bonusy"}, {"s": "kak-bez-protsentov-perevesti-dengi-s-karty-vtb-na-kartu-sberbanka", "t": "Как перевести деньги с карты ВТБ на Сбербанк без процентов в 2026 году", "i": "💸", "c": "perevody"}, {"s": "kak-bez-protsentov-perevesti-dengi-so-sberbanka-na-vtb-bez-komissii", "t": "Как перевести деньги со Сбербанка на ВТБ без комиссии: 5 способов", "i": "💸", "c": "perevody"}, {"s": "kak-bez-protsentov-perevesti-s-vtb-na-sberbank-dengi-v-prilozhenie", "t": "Как перевести деньги с ВТБ на Сбербанк без комиссии в 2026 году", "i": "💸", "c": "perevody"}, {"s": "kak-bystree-pogasit-potrebitelskij-kredit-v-vtb-24", "t": "Как быстрее погасить кредит в ВТБ 24: 7 работающих способов 2026", "i": "📉", "c": "kredity"}, {"s": "kak-bystree-vyplatit-kredit-v-vtb-24-sovety", "t": "Как быстрее погасить кредит в ВТБ: 24 проверенных совета 2026", "i": "📉", "c": "kredity"}, {"s": "kak-bystro-nachislyaetsya-keshbek-v-vtb", "t": "Скорость начисления кэшбэка в ВТБ: сроки и нюансы 2026 года", "i": "🎁", "c": "bonusy"}, {"s": "kak-bystro-pogasit-kredit-v-vtb", "t": "Как быстро погасить кредит в ВТБ: 7 работающих способов 2026", "i": "📉", "c": "kredity"}, {"s": "kak-bystro-poluchit-kartu-vtb-24", "t": "Как быстро получить карту ВТБ 24: пошаговая инструкция 2026", "i": "💳", "c": "karty-i-scheta"}, {"s": "kak-bystro-postupayut-dengi-na-vtb", "t": "Скорость зачисления денег на карту ВТБ: сроки и нюансы 2026", "i": "💸", "c": "perevody"}, {"s": "kak-bystro-pristavy-blokiruyut-kartu-vtb", "t": "Как быстро приставы блокируют карту ВТБ: сроки и действия 2026", "i": "💳", "c": "karty-i-scheta"}, {"s": "kak-bystro-vtb-perevodit-dengi-prodavtsu", "t": "Скорость переводов ВТБ продавцам: сроки и нюансы 2026", "i": "💸", "c": "perevody"}, {"s": "kak-bystro-dayut-kredit-v-vtb", "t": "Сколько времени занимает оформление кредита в ВТБ в 2026 году", "i": "📉", "c": "kredity"}, {"s": "kak-bystro-prikhodit-keshbek-vtb", "t": "Сроки зачисления кэшбэка ВТБ в 2026 году: когда ждать деньги?", "i": "🎁", "c": "bonusy"}, {"s": "kak-bystro-soedinitsya-s-operatorom-vtb", "t": "Как быстро связаться с оператором ВТБ: 7 проверенных способов", "i": "📍", "c": "ofisy-i-bankomaty"}, {"s": "kak-bystro-vtb-perevodit-dengi", "t": "Скорость переводов ВТБ: сроки и способы зачисления денег в 2026 году", "i": "💸", "c": "perevody"}, {"s": "kak-bystro-zarabotat-na-investitsiyakh-v-vtb", "t": "Как быстро заработать на инвестициях в ВТБ: 7 проверенных способов 2026", "i": "📈", "c": "investitsii"}, {"s": "kak-byt-esli-zabyl-pin-kod-karty-vtb", "t": "Забыл ПИН-код карты ВТБ: как восстановить доступ в 2026 году", "i": "💳", "c": "karty-i-scheta"}, {"s": "kak-besprotsentno-perevesti-dengi-s-vtb-na-sberbank-bez-komissii", "t": "Как без комиссии перевести деньги с ВТБ на Сбербанк: все способы 2026", "i": "💸", "c": "perevody"}, {"s": "kak-bonusy-vtb-perevesti-v-rubli-v-mobilnom-prilozhenii", "t": "Как перевести бонусы ВТБ в рубли: пошаговая инструкция", "i": "🎁", "c": "bonusy"}, {"s": "kak-bank-vtb-obmanyvaet-po-ipoteke", "t": "ВТБ ипотека: скрытые комиссии и реальные риски для заемщика", "i": "🏠", "c": "ipoteka"}, {"s": "kak-bystro-delayut-kartu-mir-v-vtb", "t": "Как быстро делают карту ВТБ: сроки и способы получения", "i": "💳", "c": "karty-i-scheta"}, {"s": "kak-bez-komissii-perevesti-dengi-s-sberbanka-na-vtb-kartu", "t": "Как без комиссии перевести деньги с Сбербанка на карту ВТБ", "i": "💸", "c": "perevody"}, {"s": "kak-blokiruyut-kartu-vtb", "t": "Как блокируют карту ВТБ: причины, методы и способы разблокировки", "i": "🔒", "c": "bezopasnost"}, {"s": "kak-bystro-vtb-snimaet-obremenenie", "t": "Как быстро ВТБ снимает обременение: сроки и порядок действий", "i": "🏠", "c": "ipoteka"}, {"s": "kak-besplatno-perevesti-dengi-s-karty-vtb-na-kartu-sberbanka-bez-komissii", "t": "Перевод с ВТБ на Сбербанк без комиссии: 5 способов 2026", "i": "💸", "c": "perevody"}, {"s": "kak-bystro-postupayut-dengi-na-raschetnyj-schet-vtb", "t": "Как быстро поступают деньги на расчетный счет ВТБ: сроки и лимиты", "i": "💸", "c": "perevody"}, {"s": "kak-bystro-dengi-postupayu-na-schet-v-vtb", "t": "Как быстро поступают деньги на счет в ВТБ: сроки и лимиты", "i": "💸", "c": "perevody"}, {"s": "kak-bystro-dengi-postupayut-na-schet-vtb", "t": "Как быстро деньги поступают на счет ВТБ: время зачисления", "i": "💸", "c": "perevody"}, {"s": "kak-besplatno-perevesti-dengi-s-vtb-na-sberbank-bez-komissii", "t": "Как перевести деньги с ВТБ на Сбербанк без комиссии: все способы", "i": "💸", "c": "perevody"}, {"s": "kak-bystro-poluchit-kartu-vtb-banka", "t": "Как быстро получить карту ВТБ: пошаговая инструкция 2026", "i": "💳", "c": "karty-i-scheta"}, {"s": "kak-bystro-snimayut-obremenenie-s-kvartiry-posle-vyplaty-ipoteki-vtb", "t": "Снятие обременения ВТБ после ипотеки: сроки и инструкция", "i": "🏠", "c": "ipoteka"}, {"s": "kak-besplatno-perevesti-so-sberbanka-na-vtb", "t": "Как бесплатно перевести со Сбербанка на ВТБ: все способы 2026", "i": "💸", "c": "perevody"}, {"s": "kak-brat-v-arendu-velosiped-vtb", "t": "Аренда велосипеда ВТБ: как взять и оплатить через приложение", "i": "📁", "c": null}, {"s": "kak-bystro-delaetsya-karta-mir-v-vtb", "t": "Как быстро делается карта Мир в ВТБ: сроки и нюансы", "i": "💳", "c": "karty-i-scheta"}, {"s": "kak-bystro-otkryt-schet-v-vtb-fizicheskomu-litsu", "t": "Как быстро открыть счет в ВТБ физическому лицу: пошаговая инструкция", "i": "💳", "c": "karty-i-scheta"}, {"s": "kak-bystro-proiskhodit-vozvrat-deneg-na-kartu-vtb", "t": "Как быстро происходит возврат денег на карту ВТБ: сроки и правила", "i": "💳", "c": "karty-i-scheta"}, {"s": "kak-bystree-pogasit-kredit-v-vtb-pravilno-dosrochno", "t": "Как правильно погасить кредит в ВТБ досрочно: инструкция", "i": "📉", "c": "kredity"}, {"s": "kak-bystro-vtb-podaet-v-sud", "t": "Через сколько ВТБ подает в суд по кредиту: сроки и риски", "i": "📉", "c": "kredity"}, {"s": "kak-bonusy-v-vtb-potratit-v-burger", "t": "Как потратить бонусы ВТБ в Бургер Кинг: Инструкция", "i": "🎁", "c": "bonusy"}, {"s": "kak-bystro-poluchit-zakladnuyu-v-vtb-24", "t": "Как быстро получить закладную в ВТБ: пошаговая инструкция", "i": "🏠", "c": "ipoteka"}, {"s": "kak-bystro-pogasit-kreditnuyu-kartu-vtb-otzyvy", "t": "Как быстро погасить кредитную карту ВТБ: отзывы и стратегии", "i": "📉", "c": "kredity"}, {"s": "kak-borotsya-s-bankom-vtb", "t": "Как бороться с банком ВТБ: права клиентов и алгоритм действий", "i": "🔒", "c": "bezopasnost"}, {"s": "kak-bystro-vtb-delaet-debetovuyu-kartu", "t": "Сколько времени делается дебетовая карта ВТБ: сроки и нюансы", "i": "💳", "c": "karty-i-scheta"}, {"s": "kak-bez-komissii-perevesti-dengi-so-sberbanka-na-vtb-cherez-onlajn-bank-mezhdu-svoimi-schetami", "t": "Перевод со Сбербанка на ВТБ без комиссии: Инструкция", "i": "💸", "c": "perevody"}, {"s": "kak-bez-komissii-perevesti-so-sberbanka-na-vtb", "t": "Как перевести со Сбербанка на ВТБ без комиссии: способы и лимиты", "i": "💸", "c": "perevody"}, {"s": "kak-bystro-oformit-debetovuyu-kartu-vtb", "t": "Как быстро оформить дебетовую карту ВТБ: пошаговая инструкция", "i": "💳", "c": "karty-i-scheta"}, {"s": "kak-bystro-pogasit-ipoteku-v-vtb", "t": "Как быстро погасить ипотеку в ВТБ: стратегии и комиссии", "i": "🏠", "c": "ipoteka"}, {"s": "kak-bystro-spisyvayutsya-dengi-s-arestovannogo-scheta-vtb", "t": "Как быстро списываются деньги с арестованного счета ВТБ", "i": "💳", "c": "karty-i-scheta"}, {"s": "kak-bystro-raskryvaetsya-akkreditiv-v-vtb", "t": "Как быстро раскрывается аккредитив в ВТБ: сроки и условия", "i": "📁", "c": null}, {"s": "kak-bystro-vtb-odobryaet-ipoteku", "t": "Как быстро ВТБ одобряет ипотеку: сроки и этапы", "i": "🏠", "c": "ipoteka"}, {"s": "kak-bystro-prikhodit-otkaz-po-ipoteke-v-vtb", "t": "Как быстро приходит отказ по ипотеке в ВТБ: сроки и причины", "i": "🏠", "c": "ipoteka"}, {"s": "kak-bystro-vtb-zakryvaet-iis", "t": "Как быстро ВТБ закрывает ИИС: сроки и порядок действий", "i": "📈", "c": "investitsii"}, {"s": "kak-besplatno-perevesti-dengi-so-sberbanka-na-vtb", "t": "Как бесплатно перевести деньги со Сбербанка на ВТБ: все способы", "i": "💸", "c": "perevody"}, {"s": "kak-bez-komissii-snyat-dengi-s-kreditnoj-karty-vtb-24", "t": "Как снять деньги с кредитки ВТБ без комиссии: 5 проверенных способов", "i": "📉", "c": "kredity"}, {"s": "kak-bonusy-vtb-perevesti-v-rubli-na-kartu-na-telefone", "t": "Как бонусы ВТБ перевести в рубли на карту", "i": "🎁", "c": "bonusy"}, {"s": "kak-bronirovat-velosiped-vtb", "t": "Как забронировать велосипед ВТБ: пошаговая инструкция", "i": "📱", "c": "mobilnyj-bank"}, {"s": "kak-bystree-zakryt-ipoteku-v-vtb-24-kalkulyator", "t": "Как быстрее закрыть ипотеку в ВТБ: стратегии и калькулятор", "i": "🏠", "c": "ipoteka"}, {"s": "kak-bystro-zakryt-potrebitelskij-kredit-v-vtb", "t": "Как быстро закрыть потребительский кредит в ВТБ: способы и условия", "i": "📉", "c": "kredity"}, {"s": "kak-bystree-zaplatit-kredit-v-vtb", "t": "Как быстрее погасить кредит в ВТБ: стратегии и способы", "i": "📉", "c": "kredity"}, {"s": "kak-bez-komissii-perevesti-s-kivi-na-vtb", "t": "Как перевести с Киви на ВТБ без комиссии: актуальные способы", "i": "💸", "c": "perevody"}, {"s": "kak-bonusnye-bally-vtb-perevesti-v-dengi-na-kartu", "t": "Как перевести бонусные баллы ВТБ в деньги на карту", "i": "🎁", "c": "bonusy"}, {"s": "kak-brat-velosipedy-vtb", "t": "Как взять велосипед в ВТБ: условия аренды и тарифы", "i": "📁", "c": "drugoe"}, {"s": "kak-besprotsentno-snyat-dengi-s-kreditnoj-karty-vtb", "t": "Как снять деньги с кредитной карты ВТБ без процентов: инструкции", "i": "📉", "c": "kredity"}, {"s": "kak-basketbol-edinaya-liga-vtb", "t": "Баскетбол: Единая Лига ВТБ — история и формат", "i": "📁", "c": "drugoe"}, {"s": "kak-bystro-delaetsya-karta-vtb", "t": "Как быстро делается карта ВТБ: сроки, нюансы и ускорение", "i": "💳", "c": "karty-i-scheta"}, {"s": "kak-bystro-oformit-ipoteku-v-vtb-24", "t": "Как быстро оформить ипотеку в ВТБ 24: пошаговая инструкция", "i": "🏠", "c": "ipoteka"}, {"s": "kak-besplatno-popolnit-kartu-vtb-s-drugogo-banka", "t": "Как бесплатно пополнить карту ВТБ с другого банка: способы", "i": "💸", "c": "perevody"}, {"s": "kak-bystro-vtb-rassmatrivaet-zayavku-na-ipoteku", "t": "Сроки рассмотрения ипотеки в ВТБ: как быстро дают ответ?", "i": "🏠", "c": "ipoteka"}, {"s": "kak-besplatno-perevodit-s-vtb-na-sber", "t": "Как бесплатно переводить с ВТБ на Сбер: все способы 2026", "i": "💸", "c": "perevody"}, {"s": "kak-blokiruetsya-karta-vtb", "t": "Как блокируется карта ВТБ: причины и способы разблокировки", "i": "💳", "c": "karty-i-scheta"}, {"s": "kak-bez-komissii-perevesti-dengi-s-karty-vtb-na-kartu-sberbanka-v-lichnom-kabinete", "t": "Как перевести с карты ВТБ на Сбербанк без комиссии: Личный кабинет", "i": "💸", "c": "perevody"}, {"s": "kak-brat-velosipedy-vtb-naprokat", "t": "Велосипеды ВТБ напрокат: как пользоваться и тарифы", "i": "📁", "c": "drugoe"}, {"s": "kak-besplatno-perevesti-dengi-s-karty-vtb-na-kartu-sberbanka-bez-komissii-po-nomeru-telefona", "t": "Перевод с карты ВТБ на Сбербанк без комиссии по номеру телефона", "i": "💸", "c": "perevody"}, {"s": "kak-bystro-pogasit-ipoteku-v-vtb-24", "t": "Как быстро погасить ипотеку в ВТБ: стратегии и условия", "i": "🏠", "c": "ipoteka"}, {"s": "kak-bez-komissii-perevesti-dengi-s-kreditnoj-karty-vtb", "t": "Как перевести деньги с кредитной карты ВТБ без комиссии: способы", "i": "📉", "c": "kredity"}, {"s": "kak-bank-mozhet-vzyskat-zadolzhennost-po-kreditu-vtb", "t": "Взыскание долга ВТБ: права банка и действия должника", "i": "📉", "c": "kredity"}, {"s": "kak-blokirovat-kartu-vtb-v-onlajn-banke", "t": "Как заблокировать карту ВТБ в онлайн банке: пошаговая инструкция", "i": "🔒", "c": "bezopasnost"}, {"s": "kak-bonusy-vtb-perevesti-v-rubli-na-kartu-cherez-prilozhenie-multi-bonus-vtb-poshagovo", "t": "Как бонусы ВТБ перевести в рубли на карту через приложение Мультибонус", "i": "🎁", "c": "bonusy"}, {"s": "kak-bez-protsentov-perevesti-dengi-s-vtb-na-sberbank-bez-komissii-onlajn", "t": "Перевод с ВТБ на Сбербанк без комиссии: 5 способов онлайн", "i": "💸", "c": "perevody"}, {"s": "kak-brat-veliki-vtb-naprokat", "t": "Как брать велики ВТБ напрокат: аренда и подписка", "i": "📁", "c": null}, {"s": "kak-bystro-vydayut-kredit-v-vtb", "t": "Как быстро ВТБ выдает кредит: сроки и этапы 2026", "i": "📉", "c": "kredity"}, {"s": "kak-blokirovat-lichnyj-kabinet-vtb", "t": "Как заблокировать личный кабинет ВТБ: пошаговая инструкция", "i": "🔒", "c": "bezopasnost"}, {"s": "kak-bystro-zakryvaetsya-iis-v-vtb", "t": "Как быстро закрывается ИИС в ВТБ: сроки и условия", "i": "📈", "c": "investitsii"}, {"s": "kak-bez-protsentov-perevodit-dengi-s-vtb-na-sberbank", "t": "Как переводить деньги с ВТБ на Сбербанк без комиссии: методы", "i": "💸", "c": "perevody"}, {"s": "kak-bonusy-spasibo-perevesti-v-dengi-na-kartu-vtb", "t": "Как перевести бонусы Спасибо от Сбербанка в деньги на карту ВТБ", "i": "🎁", "c": "bonusy"}, {"s": "kak-bystro-pogasit-ipoteku-v-vtb-skhema", "t": "Как быстро погасить ипотеку в ВТБ: схемы и стратегии", "i": "🏠", "c": "ipoteka"}, {"s": "kak-besplatno-perevesti-s-vtb-na-sberbank-bez-komissii-onlajn", "t": "Перевод с ВТБ на Сбербанк без комиссии: инструкция онлайн", "i": "💸", "c": "perevody"}, {"s": "kak-brat-kredit-v-vtb-onlajn", "t": "Как взять кредит в ВТБ онлайн: пошаговая инструкция", "i": "📉", "c": "kredity"}, {"s": "kak-bystro-pristavy-snimayut-dengi-s-karty-posle-zachisleniya-vtb", "t": "Как быстро приставы снимают деньги с карты ВТБ: сроки и порядок", "i": "💳", "c": "karty-i-scheta"}, {"s": "kak-bonusy-vtb-perevesti-v-rubli-na-kartu-cherez-prilozhenie", "t": "Как бонусы ВТБ перевести в рубли на карту: инструкция", "i": "🎁", "c": "bonusy"}, {"s": "kak-bystro-poluchit-status-kvalifitsirovannogo-investora-v-vtb", "t": "Как стать квалифицированным инвестором в ВТБ: пошаговая инструкция", "i": "📈", "c": "investitsii"}, {"s": "kak-bonusy-na-vtb-perevesti-v-rubli-na-kartu", "t": "Как вывести бонусы ВТБ в рубли на карту: инструкция", "i": "🎁", "c": "bonusy"}, {"s": "kak-bystro-proverit-balans-karty-vtb", "t": "Как проверить баланс карты ВТБ: все способы 2026", "i": "💳", "c": "karty-i-scheta"}, {"s": "kak-bally-vtb-perevesti-v-dengi-na-kartu", "t": "Как баллы ВТБ перевести в деньги на карту: инструкция", "i": "🎁", "c": "bonusy"}, {"s": "kak-bystro-vozvrashchayutsya-dengi-s-vajldberriz-na-kartu-vtb", "t": "Как быстро возвращаются деньги с Wildberries на карту ВТБ: сроки", "i": "💳", "c": "karty-i-scheta"}, {"s": "kak-besplatno-perevesti-dengi-s-vtb-na-sberbank", "t": "Как бесплатно перевести деньги с ВТБ на Сбербанк: все способы", "i": "💸", "c": "perevody"}, {"s": "kak-bez-protsentov-perevesti-dengi-s-vtb-na-kartu-sberbanka-mezhdu-svoimi-schetami", "t": "Как перевести деньги с ВТБ на Сбер без комиссии: Инструкция", "i": "💸", "c": "perevody"}, {"s": "kak-bystro-sdelat-kartu-vtb", "t": "Как быстро сделать карту ВТБ: пошаговая инструкция и сроки", "i": "💳", "c": "karty-i-scheta"}, {"s": "kak-bystro-vtb-snimaet-obremenenie-posle-vyplaty-ipoteki", "t": "Как быстро ВТБ снимает обременение после выплаты ипотеки: сроки и порядок действий", "i": "🏠", "c": "ipoteka"}, {"s": "kak-bystro-vyvesti-dengi-s-brokerskogo-scheta-vtb-na-kartu", "t": "Как вывести деньги с брокерского счета ВТБ на карту: инструкция", "i": "📈", "c": "investitsii"}, {"s": "kak-bystro-odobryayut-kredit-v-vtb", "t": "Как быстро одобряют кредит в ВТБ: сроки, этапы и советы", "i": "📉", "c": "kredity"}, {"s": "kak-bystro-prikhodyat-dengi-s-vtb-na-sberbank", "t": "Как быстро приходят деньги с ВТБ на Сбербанк: сроки и лимиты", "i": "💸", "c": "perevody"}, {"s": "kak-bystro-prikhodyat-perevody-s-vtb-na-sberbank", "t": "Как быстро приходят переводы с ВТБ на Сбербанк: время и лимиты", "i": "💸", "c": "perevody"}, {"s": "kak-bystro-vydayut-kredit-v-vtb-banke", "t": "Как быстро выдают кредит в ВТБ: сроки и условия 2026", "i": "📉", "c": "kredity"}, {"s": "kak-bystro-snyat-obremenenie-v-vtb", "t": "Как быстро снять обременение в ВТБ: пошаговая инструкция", "i": "🏠", "c": "ipoteka"}, {"s": "kak-bystro-vtb-vozvrashchaet-dengi-na-kartu", "t": "Как быстро ВТБ возвращает деньги на карту: сроки и нюансы", "i": "💸", "c": "perevody"}, {"s": "kak-bez-protsentov-snyat-dengi-s-kreditnoj-karty-vtb-24", "t": "Как снять деньги с кредитки ВТБ без процентов: схемы и лимиты", "i": "📉", "c": "kredity"}, {"s": "kak-bez-protsentov-snyat-dengi-s-kreditnoj-karty-vtb", "t": "Как снять деньги с кредитки ВТБ без процентов: схемы и условия", "i": "💳", "c": "karty-i-scheta"}, {"s": "kak-bystro-rassmatrivayut-zayavlenie-na-ipoteku-vtb", "t": "Сколько рассматривают заявку на ипотеку в ВТБ: сроки и этапы", "i": "🏠", "c": "ipoteka"}, {"s": "kak-bystro-arestovyvayut-vtb", "t": "Сроки ареста счета в ВТБ: как быстро блокируют деньги", "i": "🔒", "c": "bezopasnost"}, {"s": "kak-bonusy-perevesti-v-rubli-karta-vtb", "t": "Как бонусы перевести в рубли: карта ВТБ и Мультибонус", "i": "🎁", "c": "bonusy"}, {"s": "kak-bystree-pogasit-ipoteku-v-vtb-i-vygodnee-otzyvy", "t": "Как быстрее погасить ипотеку в ВТБ: стратегии и отзывы 2026", "i": "🏠", "c": "ipoteka"}, {"s": "kak-bystro-dayut-kredit-v-vtb-24", "t": "Как быстро дают кредит в ВТБ: сроки, условия и нюансы", "i": "📉", "c": "kredity"}, {"s": "kak-bystro-vtb-perevodit-dengi-za-ipoteku", "t": "Сроки зачисления ипотеки ВТБ: сколько дней ждать деньги", "i": "🏠", "c": "ipoteka"}, {"s": "kak-besplatno-delat-perevody-s-vtb-na-sberbank", "t": "Как бесплатно переводить деньги с ВТБ на Сбербанк: все способы", "i": "💸", "c": "perevody"}, {"s": "kak-bezopasno-obnovit-prilozhenie-vtb-onlajn", "t": "Как безопасно обновить приложение ВТБ Онлайн: пошаговая инструкция", "i": "📁", "c": null}, {"s": "kak-besplatno-perevesti-dengi-s-karty-vtb-na-sber", "t": "Как бесплатно перевести деньги с карты ВТБ на Сбер: 4 способа", "i": "📁", "c": null}, {"s": "kak-besplatno-uznat-balans-karty-vtb", "t": "Как бесплатно узнать баланс карты ВТБ: все способы", "i": "📱", "c": "mobilnyj-bank"}, {"s": "kak-bystro-prikhodyat-dengi-vtb", "t": "Как быстро приходят деньги в ВТБ: лимиты и сроки", "i": "💸", "c": "perevody"}, {"s": "kak-bystro-razblokirovat-kartu-vtb", "t": "Как быстро разблокировать карту ВТБ: пошаговая инструкция", "i": "💳", "c": "karty-i-scheta"}, {"s": "kak-bystro-vyplatit-kredit-v-vtb", "t": "Как быстро выплатить кредит в ВТБ: стратегии и расчеты", "i": "📉", "c": "kredity"}, {"s": "kak-bonusy-na-vtb-perevesti-v-rubli-na-kartu-poshagovo-cherez-telefon", "t": "Как бонусы ВТБ перевести в рубли на карту: инструкция", "i": "🎁", "c": "bonusy"}, {"s": "kak-bystro-prikhodit-zarplata-na-kartu-vtb", "t": "Как быстро приходит зарплата на карту ВТБ: сроки и лимиты", "i": "📁", "c": null}]