[{"s": "tsifrovaya-debetovaya-karta-vtb-kak-polzovatsya", "t": "Цифровая дебетовая карта ВТБ: как оформить и пользоваться в 2026 году", "i": "💳", "c": "karty-i-scheta"}, {"s": "tseli-v-vtb-kak-rabotaet", "t": "Цели в ВТБ: как работает сервис накоплений и достижений", "i": "🐷", "c": "vklady"}, {"s": "tsifrovaya-karta-vtb-mir-chto-eto", "t": "Цифровая карта ВТБ «Мир»: что это, как оформить и пользоваться", "i": "💳", "c": "karty-i-scheta"}, {"s": "tsifrovaya-multikarta-mir-vtb-kak-polzovatsya", "t": "Цифровая мультикарта «Мир» ВТБ: как пользоваться в 2026 году", "i": "💳", "c": "karty-i-scheta"}, {"s": "tsifrovaya-qr-karta-vtb-chto-eto", "t": "Цифровая QR-карта ВТБ: что это и как пользоваться в 2026 году", "i": "💳", "c": "karty-i-scheta"}, {"s": "tsifrovaya-karta-vtb-mir-kak-polzovatsya", "t": "Цифровая карта ВТБ «Мир»: как пользоваться и активировать", "i": "💳", "c": "karty-i-scheta"}, {"s": "tsentralnyj-vtb-gde", "t": "Где находится центральный офис ВТБ в Москве: адрес, схемы проезда, часы работы", "i": "📍", "c": "ofisy-i-bankomaty"}, {"s": "tsifrovaya-kreditnaya-karta-vtb-chto-eto-takoe", "t": "Цифровая карта ВТБ: что это, как оформить и пользоваться в 2026", "i": "💳", "c": "karty-i-scheta"}, {"s": "tsifrovye-servisy-vtb-ipoteka-chto-eto", "t": "Цифровые сервисы ВТБ Ипотека 2026: как оформить онлайн", "i": "🏠", "c": "ipoteka"}, {"s": "tsifrovaya-karta-vtb-chto-eto-takoe-plyusy-i-minusy-otzyvy-vladeltsev", "t": "Цифровая карта ВТБ: что это, плюсы и минусы, отзывы владельцев 2026", "i": "💳", "c": "karty-i-scheta"}, {"s": "tsifrovaya-multikarta-vtb-kak-uznat-cvt", "t": "Цифровая мультикарта ВТБ: как узнать CVV/CVC (CVT) — инструкция 2026", "i": "💳", "c": "karty-i-scheta"}, {"s": "tsifrovaya-karta-vtb-mir-chto-eto-takoe", "t": "Цифровая карта ВТБ «Мир»: что это, как оформить и пользоваться", "i": "💳", "c": "karty-i-scheta"}, {"s": "tsifrovaya-karta-vtb-chto-eto", "t": "Цифровая карта ВТБ: что это, как оформить и пользоваться в 2026 году", "i": "💳", "c": "karty-i-scheta"}, {"s": "tsifrovye-servisy-vtb-pri-ipoteke-chto-eto", "t": "Цифровые сервисы ВТБ при ипотеке 2026: как пользоваться и экономить", "i": "🏠", "c": "ipoteka"}, {"s": "tsoz-vtb-chto-eto", "t": "ЦОЗ ВТБ: что это такое и как работает в 2026 году", "i": "📱", "c": "mobilnyj-bank"}, {"s": "tsifrovaya-multikarta-vtb-chto-eto-za-karta", "t": "Цифровая мультикарта ВТБ 2026: что это, как оформить и пользоваться", "i": "💳", "c": "karty-i-scheta"}, {"s": "tsifrovaya-karta-vtb-kak-popolnit-cherez-bankomat", "t": "Как пополнить цифровую карту ВТБ через банкомат: пошаговая инструкция 2026", "i": "💳", "c": "karty-i-scheta"}, {"s": "tsifrovaya-kreditnaya-karta-vtb-kak-polzovatsya", "t": "Цифровая карта ВТБ: как оформить и пользоваться в 2026 году", "i": "💳", "c": "karty-i-scheta"}, {"s": "tsifrovaya-karta-vtb-kak-vypustit", "t": "Цифровая карта ВТБ: как выпустить за 5 минут онлайн в 2026 году", "i": "💳", "c": "karty-i-scheta"}, {"s": "tsns-vtb-chto-eto-takoe", "t": "ЦНС ВТБ — что это такое и как работает в 2026 году", "i": "💸", "c": "perevody"}, {"s": "tsifrovaya-karta-vtb-dlya-chego", "t": "Цифровая карта ВТБ: зачем нужна и как пользоваться в 2026 году", "i": "💳", "c": "karty-i-scheta"}, {"s": "tsifrovaya-multikarta-vtb-kak-snyat-dengi", "t": "Как снять деньги с цифровой мультикарты ВТБ: 5 способов 2026", "i": "💳", "c": "karty-i-scheta"}, {"s": "tsifrovaya-ipoteka-vtb-chto-eto", "t": "Цифровая ипотека ВТБ 2026: условия, процентные ставки и как оформить", "i": "🏠", "c": "ipoteka"}, {"s": "tsifrovaya-multikarta-vtb-kak-popolnit", "t": "Как пополнить цифровую мультикарту ВТБ: 7 способов 2026", "i": "💳", "c": "karty-i-scheta"}, {"s": "tsifrovaya-multikarta-vtb-kak-popolnit-schet", "t": "Как пополнить цифровую мультикарту ВТБ: 7 способов 2026", "i": "💳", "c": "karty-i-scheta"}, {"s": "tsifrovaya-multikarta-vtb-kak-snyat-nalichnye", "t": "Как снять наличные с цифровой мультикарты ВТБ: 5 способов в 2026", "i": "💳", "c": "karty-i-scheta"}, {"s": "tsifrovaya-multikarta-vtb-chto-eto-otzyvy", "t": "Цифровая мультикарта ВТБ: что это, отзывы клиентов 2026", "i": "💳", "c": "karty-i-scheta"}, {"s": "tsifrovoj-login-unk-vtb-chto-eto", "t": "Цифровой логин УНК ВТБ — что это и как пользоваться в 2026 году", "i": "🔒", "c": "bezopasnost"}, {"s": "tsifrovaya-predoplachennaya-karta-vtb-eto-chto", "t": "Цифровая предоплаченная карта ВТБ: что это, как работает и где купить", "i": "💳", "c": "karty-i-scheta"}, {"s": "tsifrovaya-karta-vtb-chto-eto-takoe-plyusy-i-minusy", "t": "Цифровая карта ВТБ 2026: что это, плюсы и минусы виртуальной карты", "i": "💳", "c": "karty-i-scheta"}, {"s": "tsifrovaya-karta-vtb-kak-rabotaet", "t": "Цифровая карта ВТБ: как работает, как оформить и пользоваться в 2026", "i": "💳", "c": "karty-i-scheta"}, {"s": "tsifrovaya-multikarta-vtb-kak-otkryt", "t": "Цифровая мультикарта ВТБ: как оформить онлайн за 10 минут", "i": "💳", "c": "karty-i-scheta"}, {"s": "tsifrovoj-login-unk-vtb-chto-eto-takoe", "t": "Цифровой логин УНК ВТБ: что это и как пользоваться в 2026 году", "i": "🔒", "c": "bezopasnost"}, {"s": "tsifrovaya-karta-vtb-chto-eto-otzyvy", "t": "Цифровая карта ВТБ: что это, отзывы клиентов 2026 года", "i": "💳", "c": "karty-i-scheta"}, {"s": "tsifrovoj-login-unk-vtb-gde-posmotret", "t": "Цифровой логин УНК ВТБ: где посмотреть и как восстановить", "i": "💳", "c": "karty-i-scheta"}, {"s": "tsifrovaya-kreditnaya-karta-vtb-chto-eto-takoe-plyusy-i-minusy", "t": "Цифровая карта ВТБ: что это, плюсы и минусы 2026", "i": "💳", "c": "karty-i-scheta"}, {"s": "tsifrovaya-multikarta-vtb-kak-zakryt", "t": "Как закрыть цифровую мультикарту ВТБ: пошаговая инструкция 2026", "i": "💳", "c": "karty-i-scheta"}, {"s": "tsifrovoj-bonus-vtb-ipoteka-chto-eto", "t": "Цифровой бонус ВТБ Ипотека: что это и как использовать", "i": "🏠", "c": "ipoteka"}, {"s": "tsik-v-vtb-chto-eto", "t": "ЦИК в ВТБ: что это, расшифровка и как проверить", "i": "📁", "c": null}, {"s": "tsifrovaya-karta-vtb-kak-posmotret-nomer", "t": "Цифровая карта ВТБ: как посмотреть номер через приложение", "i": "📱", "c": "mobilnyj-bank"}, {"s": "tsifrovaya-karta-vtb-kak-zakryt", "t": "Цифровая карта ВТБ: как закрыть и удалить навсегда", "i": "💳", "c": "karty-i-scheta"}, {"s": "tsifrovye-servisy-vtb-chto-eto", "t": "Цифровые сервисы ВТБ: что это и как пользоваться", "i": "📱", "c": "mobilnyj-bank"}, {"s": "tsifrovaya-karta-mir-vtb-kak-oformit", "t": "Цифровая карта Мир ВТБ: как оформить и активировать онлайн", "i": "💳", "c": "karty-i-scheta"}, {"s": "tsifrovye-karty-vtb-chto-eto", "t": "Цифровые карты ВТБ: что это и как ими пользоваться", "i": "💳", "c": "karty-i-scheta"}, {"s": "tsifrovaya-kreditnaya-karta-vozmozhnostej-vtb-chto-eto", "t": "Кредитная карта «Возможности» ВТБ: что это и как работает", "i": "📉", "c": "kredity"}, {"s": "tsessiya-vtb-chto-takoe", "t": "Цессия ВТБ: что это, как работает и можно ли оспорить", "i": "📉", "c": "kredity"}, {"s": "tsns-vtb-chto-eto", "t": "ЦНС ВТБ: что это такое, расшифровка и функции центра", "i": "📍", "c": "ofisy-i-bankomaty"}, {"s": "tsifrovaya-qr-karta-vtb-kak-polzovatsya", "t": "Цифровая карта ВТБ: как пользоваться QR-кодом в приложении", "i": "💳", "c": "karty-i-scheta"}, {"s": "tsifrovaya-karta-vtb-chto-eto-kak-polzovatsya-otzyvy-klientov", "t": "Цифровая карта ВТБ: что это, как пользоваться и отзывы", "i": "💳", "c": "karty-i-scheta"}, {"s": "tsentralnyj-ofis-vtb-gde-nakhoditsya", "t": "Где находится центральный офис ВТБ: адрес и контакты", "i": "📍", "c": "ofisy-i-bankomaty"}, {"s": "tsifrovaya-multikarta-vtb-dlya-chego-nuzhna", "t": "Цифровая мультикарта ВТБ: условия, кэшбэк и применение", "i": "💳", "c": "karty-i-scheta"}, {"s": "tsifrovoj-login-vtb-chto-eto", "t": "Цифровой логин ВТБ: что это и как его получить", "i": "📱", "c": "mobilnyj-bank"}, {"s": "tsifrovaya-karta-vtb-chto-eto-kak-polzovatsya", "t": "Цифровая карта ВТБ: что это, как пользоваться и подключить", "i": "💳", "c": "karty-i-scheta"}, {"s": "tsifrovaya-multikarta-vtb-kak-polzovatsya-v-bankomate", "t": "Цифровая мультикарта ВТБ в банкомате: как снять и использовать", "i": "📍", "c": "ofisy-i-bankomaty"}, {"s": "tsifrovaya-multikarta-vtb-chto-eto-takoe-otzyvy", "t": "Цифровая мультикарта ВТБ: что это, отзывы клиентов и условия", "i": "💳", "c": "karty-i-scheta"}, {"s": "tsifrovaya-multikarta-vtb-chto-eto", "t": "Цифровая мультикарта ВТБ: что это, условия и как оформить", "i": "💳", "c": "karty-i-scheta"}, {"s": "tsifrovaya-karta-vtb-dlya-chego-nuzhna", "t": "Цифровая карта ВТБ: зачем нужна, как активировать и пользоваться", "i": "💳", "c": "karty-i-scheta"}, {"s": "tsifrovaya-multikarta-vtb-kak-popolnit-cherez-bankomat", "t": "Как пополнить цифровую мультикарту ВТБ через банкомат: инструкция", "i": "💳", "c": "karty-i-scheta"}]